{"layout":{"template":"layout"},"components":[{"name":"cookie-banner","data":"cookie-banner"},{"name":"top-navigation","data":"top-navigation"},{"name":"banner","data":"banner"},{"name":"header","data":"header"},{"name":"heading1","data":"Charles McLaren"},{"name":"subheading","data":"Former Member of the House of Lords"},{"name":"roles","data":{"template":"roles","role-list":[]}},{"name":"timeline","data":{"template":"timeline","timeline-roles":[{"time-period":"Held currently","roles":[]},{"time-period":"Held in the last 20 years","roles":[{"role-type":"Parliamentary role","role-title":"Member of the House of Lords","role-dates":["23 May 1953 to 11 Nov 1999"]}]},{"time-period":1953}]}},{"name":"footer","data":"footer"}],"title":"Lord Aberconway - UK Parliament"}